apheris_utils/__init__.py
apheris_utils/_session.py
apheris_utils/artifacts/__init__.py
apheris_utils/artifacts/_artifacts.py
apheris_utils/artifacts/_files.py
apheris_utils/artifacts/_settings.py
apheris_utils/artifacts/_utils.py
apheris_utils/data/__init__.py
apheris_utils/data/_dal_client.py
apheris_utils/data/primitives/__init__.py
apheris_utils/data/primitives/_primitives.py
apheris_utils/data/primitives/_settings.py
apheris_utils/data/primitives/utils.py
apheris_utils/extras_nvflare/__init__.py
apheris_utils/extras_nvflare/job.py
apheris_utils/extras_nvflare/logging/__init__.py
apheris_utils/extras_nvflare/logging/gateway_log_sender.py
apheris_utils/extras_nvflare/logging/orchestrator_log_receiver.py
apheris_utils/extras_nvflare/logging/util.py
apheris_utils/extras_simulator/__init__.py
apheris_utils/extras_simulator/data/__init__.py
apheris_utils/extras_simulator/data/_settings.py
apheris_utils/user_api_helpers/__init__.py
apheris_utils/user_api_helpers/dataset_utils.py
apheris_utils/user_api_helpers/job_utils.py
apheris_utils/user_api_helpers/log_summary.py
apheris_utils-0.25.0.dist-info/licenses/LICENSE
apheris_utils-0.25.0.dist-info/METADATA
apheris_utils-0.25.0.dist-info/WHEEL
apheris_utils-0.25.0.dist-info/top_level.txt
apheris_utils-0.25.0.dist-info/RECORD
