Metadata-Version: 2.4
Name: apheris-utils
Version: 0.25.0
Summary: Utility functions for Apheris projects
License-File: LICENSE
Requires-Dist: pydantic==2.12.2
Requires-Dist: pydantic-settings==2.11.0
Requires-Dist: requests==2.32.5
Provides-Extra: nvflare
Requires-Dist: nvflare<2.7,>=2.4; extra == "nvflare"
Provides-Extra: simulator
Requires-Dist: apheris-auth==0.21.*; extra == "simulator"
Dynamic: description
Dynamic: license-file
Dynamic: provides-extra
Dynamic: requires-dist
Dynamic: summary
